annotation_tool/__init__.py
annotation_tool/annotation/__init__.py
annotation_tool/annotation/annotation_base.py
annotation_tool/annotation/controller.py
annotation_tool/annotation/manual/__init__.py
annotation_tool/annotation/manual/controller.py
annotation_tool/annotation/manual/main_widget.py
annotation_tool/annotation/manual/tool_widget.py
annotation_tool/annotation/modes.py
annotation_tool/annotation/retrieval/__init__.py
annotation_tool/annotation/retrieval/controller.py
annotation_tool/annotation/retrieval/main_widget.py
annotation_tool/annotation/retrieval/retrieval_backend/__init__.py
annotation_tool/annotation/retrieval/retrieval_backend/element.py
annotation_tool/annotation/retrieval/retrieval_backend/filter.py
annotation_tool/annotation/retrieval/retrieval_backend/filter_dialog.py
annotation_tool/annotation/retrieval/retrieval_backend/loader.py
annotation_tool/annotation/retrieval/retrieval_backend/query.py
annotation_tool/annotation/retrieval/retrieval_backend/queue.py
annotation_tool/annotation/retrieval/tool_widget.py
annotation_tool/annotation/timeline.py
annotation_tool/data_model/__init__.py
annotation_tool/data_model/annotation.py
annotation_tool/data_model/annotation_scheme.py
annotation_tool/data_model/dataset.py
annotation_tool/data_model/media_type.py
annotation_tool/data_model/model.py
annotation_tool/data_model/sample.py
annotation_tool/data_model/single_annotation.py
annotation_tool/dialogs/__init__.py
annotation_tool/dialogs/annotation_dialog.py
annotation_tool/dialogs/annotation_list.py
annotation_tool/dialogs/dialog_manager.py
annotation_tool/dialogs/edit_datasets.py
annotation_tool/dialogs/import_annotation_dialog.py
annotation_tool/dialogs/load_annotation_dialog.py
annotation_tool/dialogs/local_files.py
annotation_tool/dialogs/network_list.py
annotation_tool/dialogs/new_annotation_dialog.py
annotation_tool/dialogs/settings_dialog.py
annotation_tool/file_cache/__init__.py
annotation_tool/file_cache/_file_cache.py
annotation_tool/gui.py
annotation_tool-0.10.0.dist-info/LICENSE
annotation_tool-0.10.0.dist-info/METADATA
annotation_tool-0.10.0.dist-info/WHEEL
annotation_tool-0.10.0.dist-info/entry_points.txt
annotation_tool-0.10.0.dist-info/RECORD
