Metadata-Version: 2.1
Name: annotation-tool
Version: 0.10.0
Summary: Tool for annotating time series data from sources such as IMUs, MoCap, Videos and more.
Home-page: https://github.com/TUD-Patrec/annotation-tool
License: MIT
Author: Fernando Moya Rueda
Author-email: fernando.moya@cs.tu-dortmund.de
Requires-Python: >=3.8,<3.12
Classifier: License :: OSI Approved :: MIT License
Classifier: Programming Language :: Python :: 3
Classifier: Programming Language :: Python :: 3.8
Classifier: Programming Language :: Python :: 3.9
Classifier: Programming Language :: Python :: 3.10
Classifier: Programming Language :: Python :: 3.11
Requires-Dist: PyOpenGL (>=3.1.6,<4.0.0)
Requires-Dist: PyOpenGL-accelerate (>=3.1.6,<4.0.0)
Requires-Dist: PyQt6 (>=6.4.0,<7.0.0)
Requires-Dist: appdirs (>=1.4.4,<2.0.0)
Requires-Dist: decord (>=0.6.0,<0.7.0) ; sys_platform == "win32"
Requires-Dist: distinctipy (>=1.2.2,<2.0.0)
Requires-Dist: fcache (>=0.5.0,<0.6.0)
Requires-Dist: filetype (>=1.2.0,<2.0.0)
Requires-Dist: numpy (>=1.23.5,<1.24.0)
Requires-Dist: opencv-python (>=4.5.3.56,<4.6.0.0)
Requires-Dist: pyqtgraph (>=0.12.4,<0.13.0)
Requires-Dist: scipy (>=1.10.0,<2.0.0)
Requires-Dist: sortedcontainers (>=2.4.0,<3.0.0)
Requires-Dist: torch (>=2.0.0,<3.0.0)
